<?xml version="1.0"?>
<!DOCTYPE hibernate-mapping PUBLIC "-//Hibernate/Hibernate Mapping DTD 3.0//EN"
"http://hibernate.sourceforge.net/hibernate-mapping-3.0.dtd">
<!-- Generated 31 mars 2017 13:39:20 by Hibernate Tools 3.5.0.Final -->
<hibernate-mapping>
    <class name="com.ofrancois.springmvc.model.Edition" table="EDITION">
        <id name="edition_id" type="long" access="field">
            <column name="EDITION_ID" />
            <generator class="assigned" />
        </id>
        <property name="name" type="java.lang.String">
            <column name="NAME" />
        </property>
    </class>
</hibernate-mapping>
